{
  "name": "Aegis of the Heavens",
  "imageUrl": "https://cards.scryfall.io/large/front/a/9/a94f356d-4714-4500-8fb0-1ac68ec5c1cf.jpg",
  "colors": [
    "WHITE"
  ],
  "cost": [
    "WHITE",
    "ANY"
  ],
  "types": [
    "INSTANT"
  ],
  "rarity": "UNCOMMON",
  "ruleText": "Target creature gets +1/+7 until end of turn.",
  "abilities": [
    {
      "abilityType": "THAT_TARGETS_GET",
      "targets": [
        {
          "magicInstanceSelector": {
            "selectorType": "PERMANENT",
            "ofType": [
              "CREATURE"
            ]
          }
        }
      ],
      "parameters": [
        "+1/+7"
      ],
      "trigger": {
        "type": "CAST"
      }
    }
  ]
}